{
  "name": "ColumnsButton",
  "props": [
    {
      "name": "asChild",
      "type": "boolean",
      "optional": true,
      "comment": ""
    },
    {
      "name": "resource",
      "type": "string",
      "optional": true,
      "comment": ""
    },
    {
      "name": "size",
      "type": "\"default\" | \"sm\" | \"xs\" | \"lg\" | \"icon\" | \"icon-xs\" | \"icon-sm\" | \"icon-lg\" | null",
      "optional": true,
      "comment": ""
    },
    {
      "name": "storeKey",
      "type": "string",
      "optional": true,
      "comment": ""
    },
    {
      "name": "variant",
      "type": "\"link\" | \"default\" | \"secondary\" | \"destructive\" | \"outline\" | \"ghost\" | null",
      "optional": true,
      "comment": ""
    }
  ]
}
