{
  "name": "Edit",
  "props": [
    {
      "name": "actions",
      "type": "ReactNode",
      "optional": true,
      "comment": ""
    },
    {
      "name": "aside",
      "type": "ReactNode",
      "optional": true,
      "comment": "Side panel rendered alongside the form."
    },
    {
      "name": "children",
      "type": "ReactNode",
      "optional": true,
      "comment": ""
    },
    {
      "name": "className",
      "type": "string",
      "optional": true,
      "comment": ""
    },
    {
      "name": "component",
      "type": "ElementType",
      "optional": true,
      "comment": "Override the root element wrapping the form content. Defaults to 'div'."
    },
    {
      "name": "disableBreadcrumb",
      "type": "boolean",
      "optional": true,
      "comment": ""
    },
    {
      "name": "emptyWhileLoading",
      "type": "boolean",
      "optional": true,
      "comment": ""
    },
    {
      "name": "title",
      "type": "ReactNode",
      "optional": true,
      "comment": ""
    }
  ]
}
